langgraph_cli/__init__.py
langgraph_cli/__main__.py
langgraph_cli/analytics.py
langgraph_cli/cli.py
langgraph_cli/config.py
langgraph_cli/constants.py
langgraph_cli/docker.py
langgraph_cli/exec.py
langgraph_cli/progress.py
langgraph_cli/py.typed
langgraph_cli/schemas.py
langgraph_cli/templates.py
langgraph_cli/util.py
langgraph_cli/version.py
langgraph_cli-0.4.10.dist-info/METADATA
langgraph_cli-0.4.10.dist-info/WHEEL
langgraph_cli-0.4.10.dist-info/entry_points.txt
langgraph_cli-0.4.10.dist-info/licenses/LICENSE
langgraph_cli-0.4.10.dist-info/RECORD
